iris/__init__.py
iris/cli.py
iris/bot/__init__.py
iris/bot/models.py
iris/bot/_internal/__init__.py
iris/bot/_internal/emitter.py
iris/bot/_internal/iris.py
iris/decorators/__init__.py
iris/kakaolink/KakaoLinkModule.py
iris/kakaolink/__init__.py
iris/util/__init__.py
iris/util/pykv.py
irispy_client-0.2.2.dist-info/METADATA
irispy_client-0.2.2.dist-info/WHEEL
irispy_client-0.2.2.dist-info/entry_points.txt
irispy_client-0.2.2.dist-info/top_level.txt
irispy_client-0.2.2.dist-info/RECORD
