Metadata-Version: 2.4
Name: irispy-client
Version: 0.2.2
Summary: An Iris bot client in Python
Author-email: dolidolih <dolidolih@proton.me>
Project-URL: Homepage, https://github.com/dolidolih/irispy-client
Project-URL: Repository, https://github.com/dolidolih/irispy-client
Requires-Python: >=3.9
Requires-Dist: requests
Requires-Dist: websockets
Requires-Dist: pillow
Requires-Dist: httpx
